glycopeptide_feature_learning/oxonium.py
glycopeptide_feature_learning/partitions.py
glycopeptide_feature_learning/amino_acid_classification.py
glycopeptide_feature_learning/__init__.py
glycopeptide_feature_learning/matching.py
glycopeptide_feature_learning/peak_relations.py
glycopeptide_feature_learning/multinomial_regression.py
glycopeptide_feature_learning/plot.py
glycopeptide_feature_learning/utils.py
glycopeptide_feature_learning/version.py
glycopeptide_feature_learning/tool.py
glycopeptide_feature_learning/common_features.py
glycopeptide_feature_learning/approximation.py
glycopeptide_feature_learning/common.py
glycopeptide_feature_learning/data_source.py
glycopeptide_feature_learning/data/pearson.txt
glycopeptide_feature_learning/_c/peak_relations.c
glycopeptide_feature_learning/_c/__init__.py
glycopeptide_feature_learning/_c/model_types.pxd
glycopeptide_feature_learning/_c/peak_relations.pxd
glycopeptide_feature_learning/_c/model_types.cpython-39-x86_64-linux-gnu.so
glycopeptide_feature_learning/_c/data_source.cpython-39-x86_64-linux-gnu.so
glycopeptide_feature_learning/_c/data_source.c
glycopeptide_feature_learning/_c/approximation.c
glycopeptide_feature_learning/_c/amino_acid_classification.pyx
glycopeptide_feature_learning/_c/approximation.pxd
glycopeptide_feature_learning/_c/model_types.c
glycopeptide_feature_learning/_c/amino_acid_classification.pxd
glycopeptide_feature_learning/_c/peak_relations.cpython-39-x86_64-linux-gnu.so
glycopeptide_feature_learning/_c/approximation.pyx
glycopeptide_feature_learning/_c/amino_acid_classification.cpython-39-x86_64-linux-gnu.so
glycopeptide_feature_learning/_c/data_source.pxd
glycopeptide_feature_learning/_c/data_source.pyx
glycopeptide_feature_learning/_c/peak_relations.pyx
glycopeptide_feature_learning/_c/model_types.pyx
glycopeptide_feature_learning/_c/amino_acid_classification.c
glycopeptide_feature_learning/_c/approximation.cpython-39-x86_64-linux-gnu.so
glycopeptide_feature_learning-0.1.0rc0.dist-info/WHEEL
glycopeptide_feature_learning-0.1.0rc0.dist-info/LICENSE
glycopeptide_feature_learning-0.1.0rc0.dist-info/top_level.txt
glycopeptide_feature_learning-0.1.0rc0.dist-info/entry_points.txt
glycopeptide_feature_learning-0.1.0rc0.dist-info/RECORD
glycopeptide_feature_learning-0.1.0rc0.dist-info/METADATA
